lostislands
